{
  "resourceType": "MeasureReport",
  "id": "tb-hiv-coinfection-bagmati-2081-falgun",
  "status": "complete",
  "type": "summary",
  "measure": "https://iihms.gov.np/fhir/Measure/nepal-tb-hiv-coinfection",
  "subject": {
    "reference": "Location/loc-bagmati",
    "display": "Bagmati Province"
  },
  "date": "2026-05-17T13:33:31Z",
  "reporter": {
    "reference": "Organization/org-ntp",
    "display": "National Tuberculosis Programme"
  },
  "period": {
    "extension": [
      {
        "url": "https://iihms.gov.np/fhir/StructureDefinition/nepali-fiscal-period",
        "extension": [
          {
            "url": "bs-year",
            "valueInteger": 2081
          },
          {
            "url": "bs-month",
            "valueString": "Falgun"
          },
          {
            "url": "fiscal-year",
            "valueString": "2081/82"
          }
        ]
      }
    ],
    "start": "2025-02-16",
    "end": "2025-03-15"
  },
  "group": [
    {
      "id": "group-nepal-tb-hiv-coinfection",
      "population": [
        {
          "code": {
            "coding": [
              {
                "system": "http://terminology.hl7.org/CodeSystem/measure-population",
                "code": "denominator"
              }
            ]
          },
          "count": 6298964
        },
        {
          "code": {
            "coding": [
              {
                "system": "http://terminology.hl7.org/CodeSystem/measure-population",
                "code": "numerator"
              }
            ]
          },
          "count": 0
        }
      ],
      "measureScore": {
        "value": 0.0,
        "unit": "proportion",
        "system": "http://unitsofmeasure.org"
      },
      "stratifier": [
        {
          "id": "stratifier-district",
          "code": {
            "text": "District-level Disaggregation"
          },
          "stratum": [
            {
              "value": {
                "text": "DOLAKHA"
              },
              "population": [
                {
                  "code": {
                    "coding": [
                      {
                        "system": "http://terminology.hl7.org/CodeSystem/measure-population",
                        "code": "numerator"
                      }
                    ]
                  },
                  "count": 0
                },
                {
                  "code": {
                    "coding": [
                      {
                        "system": "http://terminology.hl7.org/CodeSystem/measure-population",
                        "code": "denominator"
                      }
                    ]
                  },
                  "count": 163656
                }
              ]
            },
            {
              "value": {
                "text": "SINDHUPALCHOK"
              },
              "population": [
                {
                  "code": {
                    "coding": [
                      {
                        "system": "http://terminology.hl7.org/CodeSystem/measure-population",
                        "code": "numerator"
                      }
                    ]
                  },
                  "count": 0
                },
                {
                  "code": {
                    "coding": [
                      {
                        "system": "http://terminology.hl7.org/CodeSystem/measure-population",
                        "code": "denominator"
                      }
                    ]
                  },
                  "count": 244996
                }
              ]
            },
            {
              "value": {
                "text": "RASUWA"
              },
              "population": [
                {
                  "code": {
                    "coding": [
                      {
                        "system": "http://terminology.hl7.org/CodeSystem/measure-population",
                        "code": "numerator"
                      }
                    ]
                  },
                  "count": 0
                },
                {
                  "code": {
                    "coding": [
                      {
                        "system": "http://terminology.hl7.org/CodeSystem/measure-population",
                        "code": "denominator"
                      }
                    ]
                  },
                  "count": 45618
                }
              ]
            },
            {
              "value": {
                "text": "DHADING"
              },
              "population": [
                {
                  "code": {
                    "coding": [
                      {
                        "system": "http://terminology.hl7.org/CodeSystem/measure-population",
                        "code": "numerator"
                      }
                    ]
                  },
                  "count": 0
                },
                {
                  "code": {
                    "coding": [
                      {
                        "system": "http://terminology.hl7.org/CodeSystem/measure-population",
                        "code": "denominator"
                      }
                    ]
                  },
                  "count": 310313
                }
              ]
            },
            {
              "value": {
                "text": "NUWAKOT"
              },
              "population": [
                {
                  "code": {
                    "coding": [
                      {
                        "system": "http://terminology.hl7.org/CodeSystem/measure-population",
                        "code": "numerator"
                      }
                    ]
                  },
                  "count": 0
                },
                {
                  "code": {
                    "coding": [
                      {
                        "system": "http://terminology.hl7.org/CodeSystem/measure-population",
                        "code": "denominator"
                      }
                    ]
                  },
                  "count": 255055
                }
              ]
            },
            {
              "value": {
                "text": "KATHMANDU"
              },
              "population": [
                {
                  "code": {
                    "coding": [
                      {
                        "system": "http://terminology.hl7.org/CodeSystem/measure-population",
                        "code": "numerator"
                      }
                    ]
                  },
                  "count": 0
                },
                {
                  "code": {
                    "coding": [
                      {
                        "system": "http://terminology.hl7.org/CodeSystem/measure-population",
                        "code": "denominator"
                      }
                    ]
                  },
                  "count": 2174716
                }
              ]
            },
            {
              "value": {
                "text": "BHAKTAPUR"
              },
              "population": [
                {
                  "code": {
                    "coding": [
                      {
                        "system": "http://terminology.hl7.org/CodeSystem/measure-population",
                        "code": "numerator"
                      }
                    ]
                  },
                  "count": 0
                },
                {
                  "code": {
                    "coding": [
                      {
                        "system": "http://terminology.hl7.org/CodeSystem/measure-population",
                        "code": "denominator"
                      }
                    ]
                  },
                  "count": 482501
                }
              ]
            },
            {
              "value": {
                "text": "LALITPUR"
              },
              "population": [
                {
                  "code": {
                    "coding": [
                      {
                        "system": "http://terminology.hl7.org/CodeSystem/measure-population",
                        "code": "numerator"
                      }
                    ]
                  },
                  "count": 0
                },
                {
                  "code": {
                    "coding": [
                      {
                        "system": "http://terminology.hl7.org/CodeSystem/measure-population",
                        "code": "denominator"
                      }
                    ]
                  },
                  "count": 597815
                }
              ]
            },
            {
              "value": {
                "text": "KAVREPALANCHOK"
              },
              "population": [
                {
                  "code": {
                    "coding": [
                      {
                        "system": "http://terminology.hl7.org/CodeSystem/measure-population",
                        "code": "numerator"
                      }
                    ]
                  },
                  "count": 0
                },
                {
                  "code": {
                    "coding": [
                      {
                        "system": "http://terminology.hl7.org/CodeSystem/measure-population",
                        "code": "denominator"
                      }
                    ]
                  },
                  "count": 358120
                }
              ]
            },
            {
              "value": {
                "text": "RAMECHHAP"
              },
              "population": [
                {
                  "code": {
                    "coding": [
                      {
                        "system": "http://terminology.hl7.org/CodeSystem/measure-population",
                        "code": "numerator"
                      }
                    ]
                  },
                  "count": 0
                },
                {
                  "code": {
                    "coding": [
                      {
                        "system": "http://terminology.hl7.org/CodeSystem/measure-population",
                        "code": "denominator"
                      }
                    ]
                  },
                  "count": 158015
                }
              ]
            },
            {
              "value": {
                "text": "SINDHULI"
              },
              "population": [
                {
                  "code": {
                    "coding": [
                      {
                        "system": "http://terminology.hl7.org/CodeSystem/measure-population",
                        "code": "numerator"
                      }
                    ]
                  },
                  "count": 0
                },
                {
                  "code": {
                    "coding": [
                      {
                        "system": "http://terminology.hl7.org/CodeSystem/measure-population",
                        "code": "denominator"
                      }
                    ]
                  },
                  "count": 294635
                }
              ]
            },
            {
              "value": {
                "text": "MAKAWANPUR"
              },
              "population": [
                {
                  "code": {
                    "coding": [
                      {
                        "system": "http://terminology.hl7.org/CodeSystem/measure-population",
                        "code": "numerator"
                      }
                    ]
                  },
                  "count": 0
                },
                {
                  "code": {
                    "coding": [
                      {
                        "system": "http://terminology.hl7.org/CodeSystem/measure-population",
                        "code": "denominator"
                      }
                    ]
                  },
                  "count": 467275
                }
              ]
            },
            {
              "value": {
                "text": "CHITAWAN"
              },
              "population": [
                {
                  "code": {
                    "coding": [
                      {
                        "system": "http://terminology.hl7.org/CodeSystem/measure-population",
                        "code": "numerator"
                      }
                    ]
                  },
                  "count": 0
                },
                {
                  "code": {
                    "coding": [
                      {
                        "system": "http://terminology.hl7.org/CodeSystem/measure-population",
                        "code": "denominator"
                      }
                    ]
                  },
                  "count": 746249
                }
              ]
            }
          ]
        }
      ]
    }
  ]
}